reece_calvin.py
reece_calvin-0.0.2.dist-info/METADATA
reece_calvin-0.0.2.dist-info/WHEEL
reece_calvin-0.0.2.dist-info/top_level.txt
reece_calvin-0.0.2.dist-info/RECORD
