Metadata-Version: 2.1
Name: reece-calvin
Version: 0.0.2
Summary: My reusable functions
Author: Reece Calvin
Classifier: Programming Language :: Python :: 3
Classifier: License :: OSI Approved :: MIT License
Classifier: Operating System :: OS Independent
Requires-Python: >=3.6
